temp/InstrMem.v
//`ifndef __INSTRMEM_V__
//`define __INSTRMEM_V__

`define IMEM_SIZE 256 // maximum 131072
`define IMEM_BITS 22

module instrMem(reset, addr, data_out);
	input reset;
	input [`IMEM_BITS-1:0] addr; // 2MB
	output [31:0] data_out;

	reg [31:0] memory[0:`IMEM_SIZE-1];
	integer i;

	always @ (*) begin
		if (!reset) begin
			for (i = 0; i < `IMEM_SIZE; i = i + 1)
				memory[i] <= 0;
//				memory[i] <= `IMEM_SIZE - 1 - i; // for test
		end
	end

	assign data_out = memory[addr];

endmodule // instrMem

//`endif /*__INSTRMEM_V__*/

temp/tb_instrMem.v
`timescale 1ns/1ns

`include "instrMem.v"

module tb_instrMem();
	reg reset;
	reg [21:0] address;
	wire [31:0] dataOut;

	instrMem _instrMem(reset, address, dataOut);

	initial begin
		$dumpfile("test.vcd");
		$dumpvars(-1, _instrMem);

		// reset
		#1 reset = 1;
		#1 reset = 0;

		// memory read
		#1 address = 0;
		#1 address = 1;
		#1 address = 2;
		#1 address = 3;
		#1 address = 4;
		#1 address = 5;
		#1 address = 6;
		#1 address = 7;
		#1 address = 8;
		#1 address = 255;

		#1 $finish;
	end

endmodule

temp/test.vcd
$date
	Sat Jul 24 00:47:43 2021
$end
$version
	Icarus Verilog
$end
$timescale
	1ns
$end
$scope module tb_instrMem $end
$scope module _instrMem $end
$var wire 22 ! addr [21:0] $end
$var wire 32 " data_out [31:0] $end
$var wire 1 # reset $end
$var integer 32 $ i [31:0] $end
$upscope $end
$upscope $end
$enddefinitions $end
#0
$dumpvars
bx $
x#
bx "
bx !
$end
#1
1#
#2
b100000000 $
0#
#3
b11111111 "
b0 !
#4
b11111110 "
b1 !
#5
b11111101 "
b10 !
#6
b11111100 "
b11 !
#7
b11111011 "
b100 !
#8
b11111010 "
b101 !
#9
b11111001 "
b110 !
#10
b11111000 "
b111 !
#11
b11110111 "
b1000 !
#12
b0 "
b11111111 !
